jira_git_branch_namer/__init__.py
jira_git_branch_namer/branch_naming.py
jira_git_branch_namer-1.3.dist-info/METADATA
jira_git_branch_namer-1.3.dist-info/WHEEL
jira_git_branch_namer-1.3.dist-info/entry_points.txt
jira_git_branch_namer-1.3.dist-info/RECORD
