Metadata-Version: 2.1
Name: jira_git_branch_namer
Version: 1.3
Summary: Python package designed to simplify the process of generating Git branch names based on Jira issue information
License: MIT
Author: Prakash Bhandari
Author-email: thebhandariprakash@gmail.com
Requires-Python: >=3.6.2,<4.0
Classifier: License :: OSI Approved :: MIT License
Classifier: Programming Language :: Python :: 3
Classifier: Programming Language :: Python :: 3.7
Classifier: Programming Language :: Python :: 3.8
Classifier: Programming Language :: Python :: 3.9
Classifier: Programming Language :: Python :: 3.10
Classifier: Programming Language :: Python :: 3.11
Classifier: Programming Language :: Python :: 3.12
Requires-Dist: prompt_toolkit (>=3.0.20,<4.0.0)
Requires-Dist: pyperclip (>=1.8.2,<2.0.0)
